thousandeyes_sdk/endpoint_test_results/__init__.py
thousandeyes_sdk/endpoint_test_results/py.typed
thousandeyes_sdk/endpoint_test_results/api/__init__.py
thousandeyes_sdk/endpoint_test_results/api/http_server_endpoint_scheduled_test_results_api.py
thousandeyes_sdk/endpoint_test_results/api/local_network_endpoint_test_results_api.py
thousandeyes_sdk/endpoint_test_results/api/network_dynamic_endpoint_test_results_api.py
thousandeyes_sdk/endpoint_test_results/api/network_endpoint_scheduled_test_results_api.py
thousandeyes_sdk/endpoint_test_results/api/real_user_endpoint_test_results_api.py
thousandeyes_sdk/endpoint_test_results/models/__init__.py
thousandeyes_sdk/endpoint_test_results/models/application_metrics.py
thousandeyes_sdk/endpoint_test_results/models/application_score_quality.py
thousandeyes_sdk/endpoint_test_results/models/asn_details.py
thousandeyes_sdk/endpoint_test_results/models/conditional_operator.py
thousandeyes_sdk/endpoint_test_results/models/cpu_utilization.py
thousandeyes_sdk/endpoint_test_results/models/dynamic_base_endpoint_test_result.py
thousandeyes_sdk/endpoint_test_results/models/dynamic_endpoint_test_webex.py
thousandeyes_sdk/endpoint_test_results/models/dynamic_endpoint_tests_data_round_search.py
thousandeyes_sdk/endpoint_test_results/models/dynamic_endpoint_tests_data_search_filter.py
thousandeyes_sdk/endpoint_test_results/models/dynamic_test.py
thousandeyes_sdk/endpoint_test_results/models/dynamic_test_links.py
thousandeyes_sdk/endpoint_test_results/models/dynamic_test_self_link.py
thousandeyes_sdk/endpoint_test_results/models/endpoint_agent_labels_selector_config.py
thousandeyes_sdk/endpoint_test_results/models/endpoint_agent_selector_config.py
thousandeyes_sdk/endpoint_test_results/models/endpoint_agent_to_server_test.py
thousandeyes_sdk/endpoint_test_results/models/endpoint_all_agents_selector_config.py
thousandeyes_sdk/endpoint_test_results/models/endpoint_browser.py
thousandeyes_sdk_endpoint_test_results-2.23.0.dist-info/licenses/LICENSE
thousandeyes_sdk_endpoint_test_results-2.23.0.dist-info/licenses/NOTICE
thousandeyes_sdk_endpoint_test_results-2.23.0.dist-info/METADATA
thousandeyes_sdk_endpoint_test_results-2.23.0.dist-info/WHEEL
thousandeyes_sdk_endpoint_test_results-2.23.0.dist-info/top_level.txt
thousandeyes_sdk_endpoint_test_results-2.23.0.dist-info/RECORD
